{
  "NBA Lakers vs Rockets series": {
    "has_edge": false,
    "signal": "none",
    "minutes_since_info": 999,
    "source": "none",
    "detail": "",
    "ts": 1777671619.0204957
  },
  "UFC Fight Night: Carlos Prates vs. Jack Della Maddalena (Wel": {
    "has_edge": false,
    "signal": "none",
    "minutes_since_info": 999,
    "source": "none",
    "detail": "",
    "ts": 1777671659.3578954
  },
  "UFC Fight Night: Themba Gorimbo vs. Jonathan Micallef (Welte": {
    "has_edge": false,
    "signal": "none",
    "minutes_since_info": 999,
    "source": "none",
    "detail": "",
    "ts": 1777671672.1964953
  },
  "Will Scottie Scheffler win the 2026 Cadillac Championship?": {
    "has_edge": false,
    "signal": "none",
    "minutes_since_info": 999,
    "source": "none",
    "detail": "",
    "ts": 1777671691.9953718
  },
  "Abidjan 2: Calvin Hemery vs Michael Mmoh": {
    "has_edge": false,
    "signal": "none",
    "minutes_since_info": 999,
    "source": "none",
    "detail": "",
    "ts": 1777671712.9965117
  },
  "Will Donald Trump announce that the United States blockade o": {
    "has_edge": false,
    "signal": "none",
    "minutes_since_info": 999,
    "source": "none",
    "detail": "",
    "ts": 1777671724.7212338
  }
}